{
  "@context": "http://schema.org",
  "@type": [
    "LodgingBusiness"
  ],
  "url": [
    "http://maps.mayrhofen.at/?foreignResource\u003d2D445C8F-F3F5-4202-9448-23C069D8716C"
  ],
  "address": {
    "@type": "PostalAddress",
    "streetAddress": "Kohlstatt 260a",
    "addressLocality": "Schwendau",
    "postalCode": "6283",
    "addressCountry": "AT",
    "telephone": "0043 5285 64179",
    "email": "brigitte.rahm@aon.at",
    "url": "http://www.fewo-rahm.at"
  },
  "name": "Rahm Brigitte",
  "description": [
    {
      "@language": "de",
      "@value": "Herzlich Willkommen! \n\nGenießen Sie Ihre Urlaubstage bei uns und fühlen Sie sich wie zu Hause. Ihre Traumferienwohnungen für Sommer und Winter. Unser Haus liegt in Schwendau im Zillertal in sehr sonniger und ruhiger Lage umgeben von Wiesen und dem Blick auf eine herrliche Bergkulisse. Die beiden Ortschaften Mayrhofen und Hippach können in ca. 5 Minuten mit dem Auto erreicht werden, die Bushaltestelle für den Gästebus liegt 2 Minuten zu Fuß entfernt. Im Winter ermöglicht unsere Toplage den direkten Einstieg in das Skigebiet Zillertal 3000. im Sommer ist unser Haus Ausgangspunkt für herrliche Wanderungen, Radtouren, Kletterpartien und vieles mehr. Wir vermieten drei Ferienwohnungen für zwei-neun Personen und würden uns sehr freuen auch Sie bald bei uns im Haus begrüßen zu dürfen.\n\nHerzlichst\nBrigitte und Hans Rahm\n"
    },
    {
      "@language": "de",
      "@value": "Am Anreisetag können die Appartements ab 14 Uhr bezogen werden."
    },
    {
      "@language": "en",
      "@value": "Enjoy your holidays with us and feel at home. Your dream holiday flats for summer and winter.\nWelcome\n\nOur house is located in the Zillertal Schwendau in a very sunny and quiet location surrounded by meadows and a view of a magnificent mountain backdrop. The two towns Mayrhofen and Hippach can be reached in about 5 minutes by car, the bus stop for the guest bus is 2 minutes walk away. In winter, our prime location provides direct access to the ski Zillertal 3,000. In summer our house is the starting point for wonderful hiking, biking, climbing and much more.\nWe rent three apartments for two-nine people and look forward to welcoming you soon also in the house with us.\n\nSincerely,\nBrigitte \u0026 Hans Rahm\n"
    },
    {
      "@language": "ru",
      "@value": "Добро пожаловать! --- Насладитесь своим отпуском у нас и чувствуйте себя как дома! Наш дом находится в Швендау в очень солнечном и спокойном месте в окружении гор. Как до Майрхофена, так и до Хиппаха Вы сможете добраться всего за 5 мин. на машине. Зимой - это отличное место для того, чтобы начать свой день с катания в зоне Zillertal 3000, летом наш дом - это отличная отправная точка чтобы погулять в горах пешком или на велосипедах. Мы сдаем 3 апартамента, к каждом из которых может разместиться от 3 до 9 человек и будем рады увидеть вас среди наших гостей.  С любовью, Бригитта и Ханс Рам."
    }
  ],
  "image": [
    {
      "@type": "ImageObject",
      "url": "http://resc.deskline.net/images/ZIL/1/e2c37309-fd22-4aa9-bfb5-25319d01bb0a/99/image.jpg",
      "caption": [
        {
          "@language": "de",
          "@value": "Brigitte Rahm Schwendau - Sommer 3"
        },
        {
          "@language": "en",
          "@value": "Brigitte Rahm Schwendau - Sommer 3"
        },
        {
          "@language": "ru",
          "@value": "Brigitte Rahm Schwendau - Sommer 3"
        }
      ]
    },
    {
      "@type": "ImageObject",
      "url": "http://resc.deskline.net/images/ZIL/1/81bc822e-a1ff-428a-8f89-13023e2ec24e/99/image.jpg",
      "caption": [
        {
          "@language": "de",
          "@value": "Brigitte Rahm Schwendau - Winter 1"
        },
        {
          "@language": "en",
          "@value": "Brigitte Rahm Schwendau - Winter 1"
        },
        {
          "@language": "ru",
          "@value": "Brigitte Rahm Schwendau - Winter 1"
        }
      ]
    },
    {
      "@type": "ImageObject",
      "url": "http://resc.deskline.net/images/ZIL/1/f5e9cacb-635a-4281-994f-00d75786f7d1/99/image.jpg",
      "caption": [
        {
          "@language": "de",
          "@value": "Brigitte Rahm Schwendau - Aussicht"
        },
        {
          "@language": "en",
          "@value": "Brigitte Rahm Schwendau - Aussicht"
        },
        {
          "@language": "ru",
          "@value": "Brigitte Rahm Schwendau - Aussicht"
        }
      ]
    },
    {
      "@type": "ImageObject",
      "url": "http://resc.deskline.net/images/ZIL/1/f69648e8-8876-4dba-b6cf-4c3247449b5b/99/image.jpg",
      "caption": [
        {
          "@language": "de",
          "@value": "Brigitte Rahm Schwendau - Sonne"
        },
        {
          "@language": "en",
          "@value": "Brigitte Rahm Schwendau - Sonne"
        },
        {
          "@language": "ru",
          "@value": "Brigitte Rahm Schwendau - Sonne"
        }
      ]
    },
    {
      "@type": "ImageObject",
      "url": "http://resc.deskline.net/images/ZIL/1/be0d35c7-2a25-45ad-89c2-28eaf9a5ca4e/99/image.jpg",
      "caption": [
        {
          "@language": "de",
          "@value": "Brigitte Rahm Schwendau - Alm"
        },
        {
          "@language": "en",
          "@value": "Brigitte Rahm Schwendau - Alm"
        },
        {
          "@language": "ru",
          "@value": "Brigitte Rahm Schwendau - Alm"
        }
      ]
    },
    {
      "@type": "ImageObject",
      "url": "http://resc.deskline.net/images/ZIL/1/9a4facc1-e54e-449d-948b-c68bf93c42a1/99/image.jpg",
      "caption": [
        {
          "@language": "de",
          "@value": "Brigitte Rahm Schwendau - Schlafzimmer"
        },
        {
          "@language": "en",
          "@value": "Brigitte Rahm Schwendau - Schlafzimmer"
        },
        {
          "@language": "ru",
          "@value": "Brigitte Rahm Schwendau - Schlafzimmer"
        }
      ]
    },
    {
      "@type": "ImageObject",
      "url": "http://resc.deskline.net/images/ZIL/1/fc383c5c-1093-4299-b6d1-ca09cda0db5d/99/image.jpg",
      "caption": [
        {
          "@language": "de",
          "@value": "Brigitte Rahm Schwendau - Wohnen"
        },
        {
          "@language": "en",
          "@value": "Brigitte Rahm Schwendau - Wohnen"
        },
        {
          "@language": "ru",
          "@value": "Brigitte Rahm Schwendau - Wohnen"
        }
      ]
    },
    {
      "@type": "ImageObject",
      "url": "http://resc.deskline.net/images/ZIL/1/676daebf-a49b-4c2d-8601-d91803a02bc5/99/image.jpg",
      "caption": [
        {
          "@language": "de",
          "@value": "Brigitte Rahm Schwendau - Badezimmer"
        },
        {
          "@language": "en",
          "@value": "Brigitte Rahm Schwendau - Badezimmer"
        },
        {
          "@language": "ru",
          "@value": "Brigitte Rahm Schwendau - Badezimmer"
        }
      ]
    },
    {
      "@type": "ImageObject",
      "url": "http://resc.deskline.net/images/ZIL/1/9a1989c3-f797-4025-ad87-7ae3e046fa12/99/image.jpg",
      "caption": [
        {
          "@language": "de",
          "@value": "Brigitte Rahm Schwendau - Küche"
        },
        {
          "@language": "en",
          "@value": "Brigitte Rahm Schwendau - Küche"
        },
        {
          "@language": "ru",
          "@value": "Brigitte Rahm Schwendau - Küche"
        }
      ]
    },
    {
      "@type": "ImageObject",
      "url": "http://resc.deskline.net/images/ZIL/1/eade509f-22e2-41f4-b04c-873e65cda878/99/image.jpg",
      "caption": [
        {
          "@language": "de",
          "@value": "Brigitte Rahm Schwendau - Wohnen 1"
        },
        {
          "@language": "en",
          "@value": "Brigitte Rahm Schwendau - Wohnen 1"
        },
        {
          "@language": "ru",
          "@value": "Brigitte Rahm Schwendau - Wohnen 1"
        }
      ]
    }
  ],
  "geo": {
    "@type": "GeoCoordinates",
    "latitude": "47.1904012",
    "longitude": "11.8595888"
  },
  "paymentAccepted": [
    "JCB",
    "MasterCard",
    "VISA"
  ],
  "currenciesAccepted": "EUR",
  "makesOffer": [
    {
      "@type": "Offer",
      "name": [
        {
          "@language": "de",
          "@value": "Appartement/Fewo, Dusche, WC, 2 Schlafräume"
        },
        {
          "@language": "en",
          "@value": "Apartment, shower, toilet, 2 bed rooms"
        },
        {
          "@language": "ru",
          "@value": "Апартамент, душ, туалет, две спальни"
        }
      ],
      "description": [
        {
          "@language": "de",
          "@value": "Unsere Wohnung ISABELLA und ANDREAS bietet mit ca. 55 m2 Platz für zwei bis fünf Personen.\nZwei Schlafzimmer, Dusche und WC, Flur mit Garderobe und eine großzügige Wohnküche mit gemütlicher Sitzecke , Ausziehcouch und Sat-TV bieten Ihnen genügend Platz um sich rundum wohl zufühlen. Ein großzügiger Balkon in Richtung Süden gibt den Blick auf unseren Hausberg AHORN frei. Die Küche ist ausgestattet mit Backofen, Vierplattenkochfeld, Kaffeemaschine, Wasserkocher, sämtlichem Koch- sowie Eßgeschirr. Bettwäsche, Handtücher, Badetücher und Küchentücher sind ebenso vorhanden. W-Lan. Gerne bestellen wir frisches Brot bei unserem Dorfbäcker für Ihr Frühstück. Parkplatz finden Sie vor unserem Haus. Ihre Skier sind in unserem Skiraum mit beheiztem Skischuhwärmer bestens verwahrt.\n"
        },
        {
          "@language": "en",
          "@value": "Our apartment ISABELLA and ANDREAS offers 55m2 for two to five guests, Two bedrooms, shower and toilet, hallway with cloakroom and a spacious kitchen with a cozy sitting area, sofa bed and satellite TV offer enough space to reach maximum ease. A large south-facing balcony offers a view on our local mountain MAPLE. The kitchen is equipped with oven, four plate hob, coffee maker, kettle, cooking and eating utensils sämtlichem. Bed linen, towels, bath towels and kitchen towels are provided. W-Lan We can order fresh bread at our village bakery for breakfast. You can find parking in front of our house. Your skis are best kept in our ski room with heated boot warmers."
        },
        {
          "@language": "ru",
          "@value": "Наши апартаменты Изабелла и Андреас, прим. 55 м³ предлагают вам размещение от 2 до 5 человек. --- Две спальни, душ и туалет, коридор и гардеробная, большая кухня-гостиная с уютной обеденной зоной, спутниковое ТВ. Большой балкон на южную сторону и видом на гору Ахорн. Кухня полностью оборудована: плита, духовка, кофеварка, чайник, посуда, постельное белье, полотенца. Wi-Fi. По вашему запросу мы доставим Вам свежий хлеб из нашей пекарни. Парковка находится прямо около нашего дома. В нашем доме есть комната, где вы можете хранить свои лыжи и есть сушка для ботинок. "
        }
      ],
      "availability": "http://schema.org/InStock",
      "itemOffered": [
        {
          "@type": [
            "Apartment",
            "Product"
          ],
          "name": [
            {
              "@language": "de",
              "@value": "Wohnung Andreas/Isabella"
            },
            {
              "@language": "en",
              "@value": "apartment/2 bedroom/shower, WC"
            },
            {
              "@language": "ru",
              "@value": "Апартамент, душ, туалет, две спальни"
            }
          ],
          "numberOfRooms": "3.0",
          "occupancy": {
            "@type": "QuantitativeValue",
            "maxValue": "5",
            "minValue": "2"
          }
        }
      ],
      "priceSpecification": [
        {
          "@type": "PriceSpecification",
          "description": "Pax 2",
          "minPrice": "38.00",
          "maxPrice": "70.00",
          "priceCurrency": "EUR"
        },
        {
          "@type": "PriceSpecification",
          "description": "Pax 3",
          "minPrice": "54.00",
          "maxPrice": "90.00",
          "priceCurrency": "EUR"
        },
        {
          "@type": "PriceSpecification",
          "description": "Pax 4",
          "minPrice": "72.00",
          "maxPrice": "120.00",
          "priceCurrency": "EUR"
        },
        {
          "@type": "PriceSpecification",
          "description": "Pax 5",
          "minPrice": "130.00",
          "maxPrice": "130.00",
          "priceCurrency": "EUR"
        }
      ]
    },
    {
      "@type": "Offer",
      "name": [
        {
          "@language": "de",
          "@value": "Appartement/Fewo, Dusche, WC, 3 Schlafräume"
        },
        {
          "@language": "en",
          "@value": "Apartment, shower, toilet, 3 bed rooms"
        },
        {
          "@language": "ru",
          "@value": "Апартамент, душ, туалет, три спальни"
        }
      ],
      "description": [
        {
          "@language": "de",
          "@value": "Unsere Wohnung AHORN bietet mit ca. 90 m2 Platz für vier bis 8 Personen.\nDrei Schlafzimmer, eines davon mit drei Betten , eines davon mit Sat-TV , zwei Duschen und zwei WC, Flur mit Garderobe und eine großzügige Wohnküche mit großem Eßtisch , Ausziehcouch und Sat-TV bieten Ihnen genügend Platz um sich rundum wohl zufühlen.\nDie zwei Balkone in Richtung Süden bzw. Osten geben den Blick auf unseren Hausberg AHORN frei. \nDie Küche ist ausgestattet mit Backofen, Vierplattenkochfeld, Kaffeemaschine, Wasserkocher, sämtlichem Koch- sowie Eßgeschirr, W-LAN. Bettwäsche, Handtücher, Badetücher und Küchentücher sind ebenso vorhanden.\nGerne bestellen wir frisches Brot bei unserem Dorfbäcker für Ihr Frühstück. Ihre Skier sind in unserem Skiraum mit beheiztem Skischuhwärmer bestens verwahrt.\n"
        },
        {
          "@language": "en",
          "@value": "Our apartment \"Ahorn\" offers 90m2 of space for four to eight guests.\nThree bedrooms, one with three beds, one with satellite TV, two showers and two toilets, hall with cloakroom and a spacious kitchen with large dining table, sofa bed and satellite TV offer enough space to reach maximum ease.\nThe two balconies to the south and east give a clear view of our local mountain AHORN. The kitchen is equipped with oven, four plate hob, coffee maker, kettle, cooking and eating utensils sämtlichem. W-LAN. Bed linen, towels, bath towels and kitchen towels are provided. We can order fresh bread at our village bakery for breakfast. Your skis are best kept in our ski room with heated boot warmers.\n"
        },
        {
          "@language": "ru",
          "@value": "Наши апартаменты Ахорн площадью 90 м2 предлагают размещение от 4 до 8 человек. 3 спальни, одна из которых с 3 кроватями, в одной из них спутниковое ТВ, 2 душа, 2 туалета, коридор с гардеробом и просторная кухня-гостиная с большим обеденным столом, спутниковым ТВ. -- 2 балкона, выходящих на юг и восток а также вид на прекрасную гору Ахонр -- В кухне есть духовка, четырехконфорочная плита, кофеварка, чайник, посуда. Wi-Fi, постельное белье, полотенца также входят в стоимость. --- С радостью по Вашему запросу доставим Вам свежий хлеб к завтраку. Ваши лыжи Вы можете хранить в нашей специальнооборудованом лыжехранилище."
        }
      ],
      "availability": "http://schema.org/InStock",
      "itemOffered": [
        {
          "@type": [
            "Apartment",
            "Product"
          ],
          "name": [
            {
              "@language": "de",
              "@value": "Wohnung Ahorn"
            },
            {
              "@language": "en",
              "@value": "Apartment, shower, toilet, 3 bed rooms"
            },
            {
              "@language": "ru",
              "@value": "апартамент, shower, toilet, 3 спальни"
            }
          ],
          "numberOfRooms": "2.0",
          "occupancy": {
            "@type": "QuantitativeValue",
            "maxValue": "8",
            "minValue": "4"
          }
        }
      ],
      "priceSpecification": [
        {
          "@type": "PriceSpecification",
          "description": "Pax 4",
          "minPrice": "80.00",
          "maxPrice": "150.00",
          "priceCurrency": "EUR"
        },
        {
          "@type": "PriceSpecification",
          "description": "Pax 5",
          "minPrice": "100.00",
          "maxPrice": "160.00",
          "priceCurrency": "EUR"
        },
        {
          "@type": "PriceSpecification",
          "description": "Pax 6",
          "minPrice": "120.00",
          "maxPrice": "180.00",
          "priceCurrency": "EUR"
        },
        {
          "@type": "PriceSpecification",
          "description": "Pax 7",
          "minPrice": "140.00",
          "maxPrice": "200.00",
          "priceCurrency": "EUR"
        },
        {
          "@type": "PriceSpecification",
          "description": "Pax 8",
          "minPrice": "160.00",
          "maxPrice": "180.00",
          "priceCurrency": "EUR"
        }
      ]
    }
  ]
}