{
  "@context": "http://schema.org",
  "@type": [
    "ClothingStore",
    "Store"
  ],
  "name": "Simpl Upstairs",
  "geo": {
    "@type": "GeoCoordinates",
    "latitude": "47.1640622",
    "longitude": "11.8617659"
  },
  "address": {
    "@type": "PostalAddress",
    "name": "Simpl Upstairs",
    "streetAddress": "Hauptstraße 459",
    "addressLocality": "Mayrhofen",
    "postalCode": "6290",
    "addressCountry": "AT",
    "telephone": "0043 5285 62786",
    "email": "mayrhofen@simpl-life-company.net",
    "url": "http://www.simpl-life-company.net/kontakt.php"
  },
  "image": [
    {
      "@type": "ImageObject",
      "url": "http://resc.deskline.net/images/ZIL/1/25f318ff-a274-42b9-813d-8d52f8a8f6fd/99/image.jpg",
      "caption": "Simpl"
    }
  ],
  "url": [
    "http://www.simpl-life-company.net/kontakt.php"
  ]
}