{
  "@context": "http://schema.org",
  "@type": [
    "LodgingBusiness"
  ],
  "url": [
    "http://www.youtube.com/embed/yMKQ2lnod-s?rel\u003d0",
    "http://maps.mayrhofen.at/?foreignResource\u003d68AE3688-E83A-4B10-BDA3-50D717C4D3D2",
    "http://www.haus-emilie.at"
  ],
  "address": {
    "@type": "PostalAddress",
    "name": "Haus Emilie",
    "streetAddress": "Ginzling 218",
    "addressLocality": "Ginzling",
    "postalCode": "6295",
    "addressCountry": "AT",
    "telephone": "0043 5286 20044",
    "email": "papilio@aon.at",
    "url": "http://www.haus-emilie.at"
  },
  "name": "Haus Emilie \u0026 Apart Papilio im Naturpark",
  "description": [
    {
      "@language": "de",
      "@value": "Haus Emilie:\nGeschmackvoll eingerichtetes Ferienhaus für 6-9 Personen mit Sauna und einem Hauch Luxus - Vollholzküche, Wohnzimmer mit Beamer, Bad mit Sauna, 4-5 Schlafzimmer, Dusche/WC.  Sie wohnen auf zwei Etagen im idyllischen Bergsteigerdorf Ginzling und werden sich in unseren großzügigen Räumen wie zu Hause fühlen. Entspannen können sie nach der Sauna auf der Couch oder auf der Ofenbank, bei einem Home-Cinema-Abend mit Beamer \u0026 Dolby-Surround-System. Trockenraum mit Skischuhtrockner \u0026 Skidepot vorhanden. W-Lan gratis.\n\nApart Papilio:\nLiebevoll eingerichtetes Apartment für 2-4 Personen. Unsere smarte Ferienwohnung liegt im Erdgeschoß im \"Haus Emilie\" im idyllischen Bergsteigerdorf Ginzling! Gut ausgestattete Wohnküche, Doppelzimmer mit Zugang zum Bad, zweites DZ liegt außerhalb der Wohnung, nur um die Ecke. Holzterrasse. Trockenraum, Skischuhtrockner, Skidepot.\n\nUnser Dorf liegt im Zillertaler Hochgebirgsnaturpark ca. 8 km hinter Mayrhofen und ist Ausgangspunkt für zahlreiche Wanderungen, Bergtouren, Kletterabenteuer im Sommer  herrliche Ski- und Gletschertage im Herbst und Winter. "
    },
    {
      "@language": "de",
      "@value": "Unser Preis beinhaltet frische Bett- und Tischwäsche, Dusch- und Handtücher.\nAn- und Abreise im Winter nur samstags, im Sommer nach Absprache.\nHaus Emilie: Die Preise verstehen sich pro Woche - für weiter Infos bitte Kontakt aufnehmen."
    },
    {
      "@language": "de",
      "@value": "Im Winter ist generell samstags der Anreisetag und das Appartement steht ihnen ab 14:00 Uhr blitzeblank zur Verfügung! (Abreise um 9:00 Uhr)\n\nIm Sommer können sie an jedem beliebigen Tag anreisen - je nach Absprache! Wir wünschen allen eine gute Fahrt\n\n"
    },
    {
      "@language": "en",
      "@value": "Tasteful furnished summer house for 6-9 people with sauna and a breath luxury - full wood kitchen, living room with video projector, bath with sauna, 4-5 bedrooms, shower / WC. You live on two floors in Ginzling and will feel in our  rooms like at your home. Ski shoe dryer, ski depot available. W-Lan for free.\n\n"
    },
    {
      "@language": "en",
      "@value": "Our price includes fresh bedclothes and table linen and towels. \nJourney and departure in winter only on Saturdays, in summer on arrangement. \nHouse Emilie: The prices get on per week - for more information get in touch please.\n"
    },
    {
      "@language": "en",
      "@value": "In winter the journey day is general Saturday and the flat stands off to you from 14:00 o\u0027clock (Departure at 9:00 o\u0027clock) \nIn summer you can arrive on each day - according to arrangement! \n"
    }
  ],
  "image": [
    {
      "@type": "ImageObject",
      "url": "http://resc.deskline.net/images/ZIL/1/c7b12946-78af-4a86-8e35-c2f01fef2acf/99/image.jpg",
      "caption": [
        {
          "@language": "de",
          "@value": "Haus Emilie Ginzling | Sommer"
        },
        {
          "@language": "en",
          "@value": "Apart Papilio"
        },
        {
          "@language": "ru",
          "@value": ""
        }
      ]
    },
    {
      "@type": "ImageObject",
      "url": "http://resc.deskline.net/images/ZIL/1/b4ba13a5-2f21-4e3c-bd40-96bce6dc77df/99/image.png",
      "caption": [
        {
          "@language": "de",
          "@value": "Logo Emilie ausgewählt"
        },
        {
          "@language": "en",
          "@value": "Logo Emilie ausgewählt"
        },
        {
          "@language": "ru",
          "@value": "Logo Emilie ausgewählt"
        }
      ]
    },
    {
      "@type": "ImageObject",
      "url": "http://resc.deskline.net/images/ZIL/1/78779993-89aa-4a7f-95d6-d6a394b11428/99/image.jpg",
      "caption": [
        {
          "@language": "de",
          "@value": "Haus Emilie Ginzling | Winter"
        },
        {
          "@language": "en",
          "@value": "Haus Emilie Ginzling | Winter"
        },
        {
          "@language": "ru",
          "@value": "Haus Emilie Ginzling | Winter"
        }
      ]
    },
    {
      "@type": "ImageObject",
      "url": "http://resc.deskline.net/images/ZIL/1/f4398933-5711-4545-8f99-097f55b1f3d1/99/image.jpg",
      "caption": [
        {
          "@language": "de",
          "@value": "Haus Emilie | Wohn- Esszimmer"
        },
        {
          "@language": "en",
          "@value": "Haus Emilie | Wohn- Esszimmer"
        },
        {
          "@language": "ru",
          "@value": "Haus Emilie | Wohn- Esszimmer"
        }
      ]
    },
    {
      "@type": "ImageObject",
      "url": "http://resc.deskline.net/images/ZIL/1/d38ad7dd-2892-4284-ad0b-e5d9d578b58b/99/image.jpg",
      "caption": [
        {
          "@language": "de",
          "@value": "Haus Emilie | Esstisch"
        },
        {
          "@language": "en",
          "@value": "Haus Emilie | Esstisch"
        },
        {
          "@language": "ru",
          "@value": "Haus Emilie | Esstisch"
        }
      ]
    },
    {
      "@type": "ImageObject",
      "url": "http://resc.deskline.net/images/ZIL/1/a1c6e049-aefe-4925-97af-5028911c17fc/99/image.jpg",
      "caption": [
        {
          "@language": "de",
          "@value": "Haus Emilie | Landhausküche"
        },
        {
          "@language": "en",
          "@value": "Haus Emilie | Landhausküche"
        },
        {
          "@language": "ru",
          "@value": "Haus Emilie | Landhausküche"
        }
      ]
    },
    {
      "@type": "ImageObject",
      "url": "http://resc.deskline.net/images/ZIL/1/2b298a98-dce1-4e64-9a82-3aa14f53938c/99/image.jpg",
      "caption": [
        {
          "@language": "de",
          "@value": "Haus Emilie | Landhausküche"
        },
        {
          "@language": "en",
          "@value": "Haus Emilie | Landhausküche"
        },
        {
          "@language": "ru",
          "@value": "Haus Emilie | Landhausküche"
        }
      ]
    },
    {
      "@type": "ImageObject",
      "url": "http://resc.deskline.net/images/ZIL/1/ac28ac9e-24d7-4479-8a3f-dd03f8d66ace/99/image.jpg",
      "caption": [
        {
          "@language": "de",
          "@value": "Haus Emilie | Schlafzimmer"
        },
        {
          "@language": "en",
          "@value": "Haus Emilie | Schlafzimmer"
        },
        {
          "@language": "ru",
          "@value": "Haus Emilie | Schlafzimmer"
        }
      ]
    },
    {
      "@type": "ImageObject",
      "url": "http://resc.deskline.net/images/ZIL/1/e4f77e5b-3fb8-462c-be3b-bb035f483d40/99/image.jpg",
      "caption": [
        {
          "@language": "de",
          "@value": "Haus Emilie | Doppelzimmer"
        },
        {
          "@language": "en",
          "@value": "Haus Emilie | Doppelzimmer"
        },
        {
          "@language": "ru",
          "@value": "Haus Emilie | Doppelzimmer"
        }
      ]
    },
    {
      "@type": "ImageObject",
      "url": "http://resc.deskline.net/images/ZIL/1/06b169de-75ca-4d12-b2e3-3e2fec6ef5b7/99/image.jpg",
      "caption": [
        {
          "@language": "de",
          "@value": "Haus Emilie | Doppelzimmer"
        },
        {
          "@language": "en",
          "@value": "Haus Emilie | Doppelzimmer"
        },
        {
          "@language": "ru",
          "@value": "Haus Emilie | Doppelzimmer"
        }
      ]
    },
    {
      "@type": "ImageObject",
      "url": "http://resc.deskline.net/images/ZIL/1/99fd386d-aa19-487c-8bbc-620487f8c7a5/99/image.jpg",
      "caption": [
        {
          "@language": "de",
          "@value": "Haus Emilie | Doppelzimmer"
        },
        {
          "@language": "en",
          "@value": "Haus Emilie | Doppelzimmer"
        },
        {
          "@language": "ru",
          "@value": "Haus Emilie | Doppelzimmer"
        }
      ]
    },
    {
      "@type": "ImageObject",
      "url": "http://resc.deskline.net/images/ZIL/1/b152c174-03fc-4de1-95f4-ed6f4fd6b018/99/image.jpg",
      "caption": [
        {
          "@language": "de",
          "@value": "Haus Emilie | Apart Papilio"
        },
        {
          "@language": "en",
          "@value": "Haus Emilie | Apart Papilio"
        },
        {
          "@language": "ru",
          "@value": "Haus Emilie | Apart Papilio"
        }
      ]
    },
    {
      "@type": "ImageObject",
      "url": "http://resc.deskline.net/images/ZIL/1/a4952500-dd0b-4a64-bf9c-5955b61bfffa/99/image.jpg",
      "caption": [
        {
          "@language": "de",
          "@value": "Haus Emilie | Ofenbank"
        },
        {
          "@language": "en",
          "@value": "Haus Emilie | Ofenbank"
        },
        {
          "@language": "ru",
          "@value": "Haus Emilie | Ofenbank"
        }
      ]
    },
    {
      "@type": "ImageObject",
      "url": "http://resc.deskline.net/images/ZIL/1/b67e9243-6907-4dc3-b574-7e7533b32178/99/image.jpg",
      "caption": [
        {
          "@language": "de",
          "@value": "Haus Emilie | Ofenbank"
        },
        {
          "@language": "en",
          "@value": "Haus Emilie | Ofenbank"
        },
        {
          "@language": "ru",
          "@value": "Haus Emilie | Ofenbank"
        }
      ]
    },
    {
      "@type": "ImageObject",
      "url": "http://resc.deskline.net/images/ZIL/1/cc511800-4944-4fe4-84d9-443cc7b993fc/99/image.jpg",
      "caption": [
        {
          "@language": "de",
          "@value": "Haus Emilie | Sauna"
        },
        {
          "@language": "en",
          "@value": "Haus Emilie | Sauna"
        },
        {
          "@language": "ru",
          "@value": "Haus Emilie | Sauna"
        }
      ]
    },
    {
      "@type": "ImageObject",
      "url": "http://resc.deskline.net/images/ZIL/1/d886cde4-59fb-40e0-b5e3-c79c3f4791a3/99/image.jpg",
      "caption": [
        {
          "@language": "de",
          "@value": "Haus Emilie Ginzling | Garten"
        },
        {
          "@language": "en",
          "@value": "Haus Emilie Ginzling | Garten"
        },
        {
          "@language": "ru",
          "@value": "Haus Emilie Ginzling | Garten"
        }
      ]
    },
    {
      "@type": "ImageObject",
      "url": "http://resc.deskline.net/images/ZIL/1/5bdc85d8-312c-450b-aff2-5a042552944f/99/image.jpg",
      "caption": [
        {
          "@language": "de",
          "@value": "Haus Emilie | Zillertaler Naturpark Partnerbetrieb"
        },
        {
          "@language": "en",
          "@value": "Haus Emilie | Zillertaler Naturpark Partnerbetrieb"
        },
        {
          "@language": "ru",
          "@value": "Haus Emilie | Zillertaler Naturpark Partnerbetrieb"
        }
      ]
    },
    {
      "@type": "ImageObject",
      "url": "http://resc.deskline.net/images/ZIL/1/06500cd4-cc81-4e45-ad51-8c36be3060d0/99/image.jpg",
      "caption": [
        {
          "@language": "de",
          "@value": "Apart Papilio | Terrasse"
        },
        {
          "@language": "en",
          "@value": "Apart Papilio | Terrasse"
        },
        {
          "@language": "ru",
          "@value": "Apart Papilio | Terrasse"
        }
      ]
    },
    {
      "@type": "ImageObject",
      "url": "http://resc.deskline.net/images/ZIL/1/73be4b40-7159-458d-8e9c-65fcd81ff197/99/image.jpg",
      "caption": [
        {
          "@language": "de",
          "@value": "Apart Papilio | Wohnküche"
        },
        {
          "@language": "en",
          "@value": "Apart Papilio | Wohnküche"
        },
        {
          "@language": "ru",
          "@value": "Apart Papilio | Wohnküche"
        }
      ]
    },
    {
      "@type": "ImageObject",
      "url": "http://resc.deskline.net/images/ZIL/1/0ba3dce6-0718-4712-9f74-21162f9ceb71/99/image.jpg",
      "caption": [
        {
          "@language": "de",
          "@value": "Apart Papilio | Doppelzimmer"
        },
        {
          "@language": "en",
          "@value": "Apart Papilio | Doppelzimmer"
        },
        {
          "@language": "ru",
          "@value": "Apart Papilio | Doppelzimmer"
        }
      ]
    },
    {
      "@type": "ImageObject",
      "url": "http://resc.deskline.net/images/ZIL/1/667e5da0-bcc2-4368-8f8c-e163721cf03c/99/image.jpg",
      "caption": [
        {
          "@language": "de",
          "@value": "Skigebiet Penken | Mayrhofen"
        },
        {
          "@language": "en",
          "@value": "Skigebiet Penken | Mayrhofen"
        },
        {
          "@language": "ru",
          "@value": "Skigebiet Penken | Mayrhofen"
        }
      ]
    }
  ],
  "geo": {
    "@type": "GeoCoordinates",
    "latitude": "47.1023451953126",
    "longitude": "11.8100827932358"
  },
  "currenciesAccepted": "EUR",
  "makesOffer": [
    {
      "@type": "Offer",
      "name": [
        {
          "@language": "de",
          "@value": "Appartement/Fewo, Dusche, WC, 4 oder mehr Schlafräume"
        },
        {
          "@language": "en",
          "@value": "Apartment, shower, toilet, 4 or more bed rooms"
        },
        {
          "@language": "ru",
          "@value": "Апартамент, душ, туалет, 4 или больше спалень"
        }
      ],
      "description": [
        {
          "@language": "de",
          "@value": "Geschmackvoll eingerichtetes Ferienhaus für 6-9 Personen, mit Sauna und einem Hauch Luxus - Vollholzküche, Wohnzimmer mit Beamer, Bad mit Sauna, 4-5 Schlafzimmer, Dusche/WC.  Es bleiben keine Wünsche offen, sie wohnen auf zwei Etagen im idyllischen Bergsteigerdorf Ginzling und werden sich in unseren großzügigen Räumen wie zu Hause fühlen."
        },
        {
          "@language": "en",
          "@value": "Tastefully decorated holiday home for 6-9 people, with sauna and a touch of luxury. Wood kitchen - well equipped, living room with a beamer and home-cinema, bathroom with sauna, 4-5 bedrooms, shower / WC. Live on two floors in the idyllic mountain village Ginzling and it feels like home... "
        }
      ],
      "availability": "http://schema.org/InStock",
      "itemOffered": [
        {
          "@type": [
            "Apartment",
            "Product"
          ],
          "name": [
            {
              "@language": "de",
              "@value": "Haus Emilie"
            },
            {
              "@language": "en",
              "@value": "Apartment, shower, toilet, 4 or more bed rooms"
            },
            {
              "@language": "ru",
              "@value": "апартамент, shower, toilet, 4 или большее количество спале"
            }
          ],
          "image": [
            {
              "@type": "ImageObject",
              "url": "http://resc.deskline.net/images/ZIL/1/73c8a063-195e-49cc-8b04-692d77021c9e/99/image.jpg",
              "caption": [
                {
                  "@language": "de",
                  "@value": "Haus Emilie"
                },
                {
                  "@language": "en",
                  "@value": ""
                },
                {
                  "@language": "ru",
                  "@value": ""
                }
              ]
            },
            {
              "@type": "ImageObject",
              "url": "http://resc.deskline.net/images/ZIL/1/a523c9fb-0959-4ceb-abec-44e919d4ea85/99/image.jpg",
              "caption": [
                {
                  "@language": "de",
                  "@value": "Haus Emilie im Winter"
                },
                {
                  "@language": "en",
                  "@value": "Haus Emilie im Winter"
                },
                {
                  "@language": "ru",
                  "@value": "Haus Emilie im Winter"
                }
              ]
            },
            {
              "@type": "ImageObject",
              "url": "http://resc.deskline.net/images/ZIL/1/bd987613-d2ad-4043-8fd1-9d0915527780/99/image.jpg",
              "caption": [
                {
                  "@language": "de",
                  "@value": "Landhausküche"
                },
                {
                  "@language": "en",
                  "@value": "Landhausküche"
                },
                {
                  "@language": "ru",
                  "@value": "Landhausküche"
                }
              ]
            }
          ],
          "numberOfRooms": "6.0",
          "occupancy": {
            "@type": "QuantitativeValue",
            "maxValue": "9",
            "minValue": "6"
          }
        }
      ],
      "priceSpecification": [
        {
          "@type": "PriceSpecification",
          "description": "Pax 6",
          "minPrice": "194.00",
          "maxPrice": "268.00",
          "priceCurrency": "EUR"
        },
        {
          "@type": "PriceSpecification",
          "description": "Pax 7",
          "minPrice": "194.00",
          "maxPrice": "268.00",
          "priceCurrency": "EUR"
        },
        {
          "@type": "PriceSpecification",
          "description": "Pax 8",
          "minPrice": "194.00",
          "maxPrice": "268.00",
          "priceCurrency": "EUR"
        },
        {
          "@type": "PriceSpecification",
          "description": "Pax 9",
          "minPrice": "216.00",
          "maxPrice": "298.00",
          "priceCurrency": "EUR"
        }
      ]
    },
    {
      "@type": "Offer",
      "name": [
        {
          "@language": "de",
          "@value": "Appartement/Fewo, Dusche, WC"
        },
        {
          "@language": "en",
          "@value": "Apartment, shower, toilet"
        },
        {
          "@language": "ru",
          "@value": "Апартамент, душ, туалет"
        }
      ],
      "description": [
        {
          "@language": "de",
          "@value": "Das \u0027Apart Papilio\u0027 ist eine abgegrenzte Ferienwohnung im Haus Emilie. Es liegt im Erdgeschoß des Hauses und bietet Platz für 2-4 Personen. Die gemütliche Wohnküche ist mit allem ausgestattet, was Sie für einen Urlaub brauchen. Die Couch kann zum Kuschelplatz umfunktioniert werden. Das eine Schlafzimmer ist direkt mit dem Badezimmer (Dusche/WC) verbunden und das zweite Schlafzimmer liegt zwar außerhalb der Fewo, aber direkt um die Ecke. Von dort kommen Sie direkt auf die feine Holzterrasse."
        },
        {
          "@language": "en",
          "@value": "The \u0027Apart Papilio\u0027 is a demarcated apartment in house Emilie. It is located on the ground floor and can accommodate 2-4 people. The cozy kitchen is equipped with everything you need for a holiday. The couch can be converted into a cuddly place. One bedroom is directly connected to the bathroom (shower / WC), and although the second bedroom is located outside the apartment but right around the corner. From there you will be directed to the fine wooden terrace."
        }
      ],
      "availability": "http://schema.org/InStock",
      "itemOffered": [
        {
          "@type": [
            "Apartment",
            "Product"
          ],
          "name": [
            {
              "@language": "de",
              "@value": "Apart Papilio"
            },
            {
              "@language": "en",
              "@value": "ap/comb.living-bedr./1 bedroom/shower,wc"
            },
            {
              "@language": "ru",
              "@value": "Апартамент, душ, туалет"
            }
          ],
          "image": [
            {
              "@type": "ImageObject",
              "url": "http://resc.deskline.net/images/ZIL/1/967980fa-cad7-4727-9c2a-2ae7b74fa5f7/99/image.jpg",
              "caption": [
                {
                  "@language": "de",
                  "@value": "Haus Emilie"
                },
                {
                  "@language": "en",
                  "@value": "Haus Emilie"
                },
                {
                  "@language": "ru",
                  "@value": "Haus Emilie"
                }
              ]
            },
            {
              "@type": "ImageObject",
              "url": "http://resc.deskline.net/images/ZIL/1/0f000d5f-15ae-4d83-99ff-7bd28aa8ae55/99/image.jpg",
              "caption": [
                {
                  "@language": "de",
                  "@value": "Wohnküche"
                },
                {
                  "@language": "en",
                  "@value": "Wohnküche"
                },
                {
                  "@language": "ru",
                  "@value": "Wohnküche"
                }
              ]
            },
            {
              "@type": "ImageObject",
              "url": "http://resc.deskline.net/images/ZIL/1/16a436c0-d843-4dec-8420-6588c9b8c13a/99/image.jpg",
              "caption": [
                {
                  "@language": "de",
                  "@value": "Haus im Winter"
                },
                {
                  "@language": "en",
                  "@value": "Haus im Winter"
                },
                {
                  "@language": "ru",
                  "@value": "Haus im Winter"
                }
              ]
            },
            {
              "@type": "ImageObject",
              "url": "http://resc.deskline.net/images/ZIL/1/dd1aab88-46ef-4a07-b870-75c8bb41440c/99/image.jpg",
              "caption": [
                {
                  "@language": "de",
                  "@value": "Schlafzimmer I"
                },
                {
                  "@language": "en",
                  "@value": "Schlafzimmer I"
                },
                {
                  "@language": "ru",
                  "@value": "Schlafzimmer I"
                }
              ]
            },
            {
              "@type": "ImageObject",
              "url": "http://resc.deskline.net/images/ZIL/1/519259a7-a01b-471b-8cfd-24df23c09206/99/image.jpg",
              "caption": [
                {
                  "@language": "de",
                  "@value": "Vorraum"
                },
                {
                  "@language": "en",
                  "@value": "Vorraum"
                },
                {
                  "@language": "ru",
                  "@value": "Vorraum"
                }
              ]
            }
          ],
          "numberOfRooms": "3.0",
          "occupancy": {
            "@type": "QuantitativeValue",
            "maxValue": "2",
            "minValue": "2"
          }
        }
      ],
      "priceSpecification": [
        {
          "@type": "PriceSpecification",
          "description": "Pax 2",
          "minPrice": "59.00",
          "maxPrice": "85.00",
          "priceCurrency": "EUR"
        }
      ]
    }
  ]
}