{
  "@context": "http://schema.org",
  "@type": [
    "LodgingBusiness"
  ],
  "url": [
    "http://www.zillertal-huette.co.at",
    "http://maps.mayrhofen.at/?foreignResource\u003dAE5DE6E3-7706-48ED-88FC-4FA48CA61437"
  ],
  "address": {
    "@type": "PostalAddress",
    "name": "Pfund, Bauernhof",
    "streetAddress": "Schwendberg 420",
    "addressLocality": "Hippach",
    "postalCode": "6283",
    "addressCountry": "AT",
    "telephone": "0043 6642736464",
    "email": "info@zillertal-huette.co.at",
    "url": "http://www.zillertal-huette.co.at"
  },
  "name": "Bauernhof Pfund",
  "description": "Prachtvolles XXL-Bauernhaus aus dem 16. Jahrhundert mit Sauna, Kachelofen und Ofenbank, der Skibushaltestelle direkt vor der Haustür und herrlicher Panorama-Aussicht bis nach Mayrhofen (1.006 m ü.M.). Das Haus ist Teil eines bewirtschafteten Hofes.",
  "image": [
    {
      "@type": "ImageObject",
      "url": "http://resc.deskline.net/images/ZIL/1/81309bf7-be0c-4c84-b7c9-aee547a88e82/99/image.jpg",
      "caption": "Bauernhof Pfund mit Blick nach Zell am Ziller"
    },
    {
      "@type": "ImageObject",
      "url": "http://resc.deskline.net/images/ZIL/1/3283e559-48d1-461c-8e59-c11936e47d66/99/image.jpg",
      "caption": "Bauernhof Pfund - Hausansicht mit neuen Balkon"
    },
    {
      "@type": "ImageObject",
      "url": "http://resc.deskline.net/images/ZIL/1/1518b3b6-8810-47fe-ab25-bbdbd73c751f/99/image.jpg",
      "caption": "große Küche"
    },
    {
      "@type": "ImageObject",
      "url": "http://resc.deskline.net/images/ZIL/1/decfe25d-d446-4a34-9d00-7e9aaab9cb97/99/image.jpg",
      "caption": "Eßecke in der Küche"
    },
    {
      "@type": "ImageObject",
      "url": "http://resc.deskline.net/images/ZIL/1/2e96ddb9-4e00-4a19-9b19-a544ec8e3053/99/image.jpg",
      "caption": "Bauernhof Pfund - Kachelofen"
    },
    {
      "@type": "ImageObject",
      "url": "http://resc.deskline.net/images/ZIL/1/81f83626-f25d-4548-98db-c9d05bcb1766/99/image.jpg",
      "caption": "Doppeldusche\u0026 Doppelwaschbecken"
    },
    {
      "@type": "ImageObject",
      "url": "http://resc.deskline.net/images/ZIL/1/7f59899b-1f83-4bcb-887d-a178385bf221/99/image.jpg",
      "caption": "Schuhtrockner\u0026 Skiabstellraum"
    },
    {
      "@type": "ImageObject",
      "url": "http://resc.deskline.net/images/ZIL/1/2ec60db1-b45b-4dc7-952f-6443a38ac7b4/99/image.jpg",
      "caption": "Bauernstube mit Kachelofen"
    },
    {
      "@type": "ImageObject",
      "url": "http://resc.deskline.net/images/ZIL/1/98fe72b5-454e-4e48-b000-6ad84902eacd/99/image.jpg",
      "caption": "Doppelzimmer"
    },
    {
      "@type": "ImageObject",
      "url": "http://resc.deskline.net/images/ZIL/1/fb36490e-e4a1-40ea-b68e-8486e15967a9/99/image.jpg",
      "caption": "Doppelzimmer"
    }
  ],
  "geo": {
    "@type": "GeoCoordinates",
    "latitude": "47.2073611073333",
    "longitude": "11.8539369106293"
  },
  "currenciesAccepted": "EUR",
  "makesOffer": [
    {
      "@type": "Offer",
      "name": "Апартамент, ванна, туалет",
      "description": "Bauernhaus Pfundhof für 6-13 Personen\nNeu!! Sauna gegen Gebühr.\nDas Haus wurde im Herbst 2011 neu und liebevoll renoviert,es ist rustikal und zweckmäßig eingerichtet, schöne Zirbenstube mit Kachelofen und Ofenbank mit Sat-TV,\nVoll ausgestattete Küche,Elektroherd mit Ceranfeld, Geschirrspüler und Mikrowelle, Kühlschrank mit Gefrierfach) 2-3 Bettzimmer, 4-2 DZ,Sauna, 2 WC, 2Bäder( 2 Duschen, 1 Badewanne),Schuhtrockner, Bushaltestelle vor dem Haus",
      "availability": "http://schema.org/InStock",
      "itemOffered": [
        {
          "@type": [
            "Apartment",
            "Product"
          ],
          "name": "Апартамент, ванна, туалет",
          "image": [
            {
              "@type": "ImageObject",
              "url": "http://resc.deskline.net/images/ZIL/1/85c7c692-cb16-448b-b817-7c46bb66c6a8/99/image.jpg",
              "caption": "Bauernhaus"
            },
            {
              "@type": "ImageObject",
              "url": "http://resc.deskline.net/images/ZIL/1/a38edc59-cfa4-4250-9f48-e6fb9ac96834/99/image.jpg",
              "caption": "Bauernhaus"
            },
            {
              "@type": "ImageObject",
              "url": "http://resc.deskline.net/images/ZIL/1/07a0129b-18f2-4d37-a8bd-49413d66ee4f/99/image.jpg",
              "caption": "Doppeldusche"
            },
            {
              "@type": "ImageObject",
              "url": "http://resc.deskline.net/images/ZIL/1/4d6b82aa-e77d-43f5-9cbb-0476f4982fcd/99/image.jpg",
              "caption": "Kachelofen"
            },
            {
              "@type": "ImageObject",
              "url": "http://resc.deskline.net/images/ZIL/1/6cb99629-7ccf-4be5-8850-9e72ada021d7/99/image.jpg",
              "caption": "Blick zum Schwendberg"
            }
          ],
          "numberOfRooms": "6.0",
          "occupancy": {
            "@type": "QuantitativeValue",
            "maxValue": "12",
            "minValue": "4"
          }
        }
      ],
      "priceSpecification": [
        {
          "@type": "PriceSpecification",
          "description": "Pax 4",
          "minPrice": "180.00",
          "maxPrice": "542.86",
          "priceCurrency": "EUR"
        },
        {
          "@type": "PriceSpecification",
          "description": "Pax 5",
          "minPrice": "180.00",
          "maxPrice": "542.86",
          "priceCurrency": "EUR"
        },
        {
          "@type": "PriceSpecification",
          "description": "Pax 6",
          "minPrice": "180.00",
          "maxPrice": "542.86",
          "priceCurrency": "EUR"
        },
        {
          "@type": "PriceSpecification",
          "description": "Pax 7",
          "minPrice": "180.00",
          "maxPrice": "542.86",
          "priceCurrency": "EUR"
        },
        {
          "@type": "PriceSpecification",
          "description": "Pax 8",
          "minPrice": "180.00",
          "maxPrice": "542.86",
          "priceCurrency": "EUR"
        },
        {
          "@type": "PriceSpecification",
          "description": "Pax 9",
          "minPrice": "180.00",
          "maxPrice": "542.86",
          "priceCurrency": "EUR"
        },
        {
          "@type": "PriceSpecification",
          "description": "Pax 10",
          "minPrice": "180.00",
          "maxPrice": "542.86",
          "priceCurrency": "EUR"
        },
        {
          "@type": "PriceSpecification",
          "description": "Pax 11",
          "minPrice": "180.00",
          "maxPrice": "542.86",
          "priceCurrency": "EUR"
        },
        {
          "@type": "PriceSpecification",
          "description": "Pax 12",
          "minPrice": "180.00",
          "maxPrice": "542.86",
          "priceCurrency": "EUR"
        }
      ]
    }
  ]
}